{
  "arch": "x86_64",
  "build": "py36hfc679d8_0",
  "build_number": 0,
  "channel": "https://conda.anaconda.org/conda-forge/linux-64",
  "constrains": [],
  "depends": [
    "libgcc-ng >=4.9",
    "libprotobuf 3.6.0.*",
    "libprotobuf >=3.6.0,<3.6.1.0a0",
    "libstdcxx-ng >=4.9",
    "python >=3.6,<3.7.0a0",
    "setuptools",
    "six"
  ],
  "features": "",
  "fn": "protobuf-3.6.0-py36hfc679d8_0.tar.bz2",
  "license": "BSD 3-Clause",
  "license_family": "BSD",
  "md5": "ef39163f53699185babd32418bfdc5b7",
  "name": "protobuf",
  "platform": "linux",
  "size": 1639323,
  "subdir": "linux-64",
  "timestamp": 1534338922472,
  "track_features": "",
  "url": "https://conda.anaconda.org/conda-forge/linux-64/protobuf-3.6.0-py36hfc679d8_0.tar.bz2",
  "version": "3.6.0"
}